.bumpversion.cfg
.coveragerc
.git_archival.txt
.gitattributes
.gitchangelog.rc
.gitignore
.stickler.yml
AUTHORS.md
CHANGELOG.md
LICENSE
README.md
RELEASING.md
setup.cfg
setup.py
.github/ISSUE_TEMPLATE.md
.github/PULL_REQUEST_TEMPLATE.md
.github/workflows/ci.yaml
.github/workflows/deploy-sdist.yaml
bin/level1c_runner.py
bin/pps2018_runner.py
bin/pps_runner.py
continuous_integration/environment.yaml
examples/l1c_runner_config.yaml
examples/log_config.yaml
examples/pps2018_config.ini_template
examples/pps2018_config.yaml_template
examples/pps2021_config.yaml_template
examples/pps_config.cfg_template
examples/pps_config.yaml
examples/pps_hooks.yaml
examples/pps_run.sh.template
nwcsafpps_runner/__init__.py
nwcsafpps_runner/config.py
nwcsafpps_runner/l1c_processing.py
nwcsafpps_runner/logger.py
nwcsafpps_runner/message_utils.py
nwcsafpps_runner/metno_update_nwp.py
nwcsafpps_runner/pps_posttroll_hook.py
nwcsafpps_runner/prepare_nwp.py
nwcsafpps_runner/publish_and_listen.py
nwcsafpps_runner/utils.py
nwcsafpps_runner.egg-info/PKG-INFO
nwcsafpps_runner.egg-info/SOURCES.txt
nwcsafpps_runner.egg-info/dependency_links.txt
nwcsafpps_runner.egg-info/not-zip-safe
nwcsafpps_runner.egg-info/requires.txt
nwcsafpps_runner.egg-info/top_level.txt
nwcsafpps_runner/tests/__init__.py
nwcsafpps_runner/tests/test_config.py
nwcsafpps_runner/tests/test_level1c_runner.py
nwcsafpps_runner/tests/test_nwp_prepare.py
nwcsafpps_runner/tests/test_pps_hook.py
nwcsafpps_runner/tests/test_utils.py
nwcsafpps_runner/tests/files/LL02_NHSF_202205100000+009H00M
nwcsafpps_runner/tests/files/LL02_NHSPSF_202205031200+009H00M
nwcsafpps_runner/tests/files/LL02_NHSP_202205100000+009H00M
workflows/ci.yaml